{
	"archive" : {},
	"artifacts" : 
	[
		{
			"path" : "libopus.a"
		}
	],
	"backtrace" : 1,
	"backtraceGraph" : 
	{
		"commands" : 
		[
			"add_library",
			"target_compile_options",
			"target_compile_definitions",
			"target_include_directories",
			"target_sources"
		],
		"files" : 
		[
			"CMakeLists.txt"
		],
		"nodes" : 
		[
			{
				"file" : 0
			},
			{
				"command" : 0,
				"file" : 0,
				"line" : 147,
				"parent" : 0
			},
			{
				"command" : 1,
				"file" : 0,
				"line" : 303,
				"parent" : 0
			},
			{
				"command" : 2,
				"file" : 0,
				"line" : 308,
				"parent" : 0
			},
			{
				"command" : 2,
				"file" : 0,
				"line" : 283,
				"parent" : 0
			},
			{
				"command" : 3,
				"file" : 0,
				"line" : 297,
				"parent" : 0
			},
			{
				"command" : 4,
				"file" : 0,
				"line" : 286,
				"parent" : 0
			}
		]
	},
	"compileGroups" : 
	[
		{
			"compileCommandFragments" : 
			[
				{
					"fragment" : "-w -DANDROID -D_LARGEFILE_SOURCE=1 -ffunction-sections -fdata-sections -fmerge-all-constants  -O3 -DNDEBUG  -fPIC"
				},
				{
					"backtrace" : 2,
					"fragment" : "-ffast-math"
				},
				{
					"backtrace" : 2,
					"fragment" : "-Os"
				},
				{
					"backtrace" : 2,
					"fragment" : "-funroll-loops"
				},
				{
					"backtrace" : 2,
					"fragment" : "-fno-strict-aliasing"
				},
				{
					"backtrace" : 2,
					"fragment" : "-fno-math-errno"
				},
				{
					"backtrace" : 2,
					"fragment" : "-fvisibility=hidden"
				}
			],
			"defines" : 
			[
				{
					"backtrace" : 3,
					"define" : "FIXED_POINT"
				},
				{
					"backtrace" : 3,
					"define" : "HAVE_LRINT"
				},
				{
					"backtrace" : 3,
					"define" : "HAVE_LRINTF"
				},
				{
					"backtrace" : 4,
					"define" : "LIBYUV_NEON"
				},
				{
					"backtrace" : 4,
					"define" : "OPUS_ARM_ASM"
				},
				{
					"backtrace" : 3,
					"define" : "OPUS_BUILD"
				},
				{
					"backtrace" : 4,
					"define" : "OPUS_HAVE_RTCD"
				},
				{
					"backtrace" : 3,
					"define" : "USE_ALLOCA"
				},
				{
					"backtrace" : 3,
					"define" : "__EMX__"
				},
				{
					"backtrace" : 3,
					"define" : "restrict="
				}
			],
			"includes" : 
			[
				{
					"backtrace" : 5,
					"path" : "/home/umerov/Open/OpenFenrir-for-VK/libfenrir/src/main/jni/audio/opus/libopus/include"
				},
				{
					"backtrace" : 5,
					"path" : "/home/umerov/Open/OpenFenrir-for-VK/libfenrir/src/main/jni/audio/opus/libopus/silk"
				},
				{
					"backtrace" : 5,
					"path" : "/home/umerov/Open/OpenFenrir-for-VK/libfenrir/src/main/jni/audio/opus/libopus/silk/fixed"
				},
				{
					"backtrace" : 5,
					"path" : "/home/umerov/Open/OpenFenrir-for-VK/libfenrir/src/main/jni/audio/opus/libopus/celt"
				},
				{
					"backtrace" : 5,
					"path" : "/home/umerov/Open/OpenFenrir-for-VK/libfenrir/src/main/jni/audio/opus/libopus"
				}
			],
			"language" : "C",
			"sourceIndexes" : 
			[
				0,
				1,
				2,
				3,
				4,
				5,
				6,
				7,
				8,
				9,
				10,
				11,
				12,
				13,
				14,
				15,
				16,
				17,
				18,
				19,
				20,
				21,
				22,
				23,
				24,
				25,
				26,
				27,
				28,
				29,
				30,
				31,
				32,
				33,
				34,
				35,
				36,
				37,
				38,
				39,
				40,
				41,
				42,
				43,
				44,
				45,
				46,
				47,
				48,
				49,
				50,
				51,
				52,
				53,
				54,
				55,
				56,
				57,
				58,
				59,
				60,
				61,
				62,
				63,
				64,
				65,
				66,
				67,
				68,
				69,
				70,
				71,
				72,
				73,
				74,
				75,
				76,
				77,
				78,
				79,
				80,
				81,
				82,
				83,
				84,
				85,
				86,
				87,
				88,
				89,
				90,
				91,
				92,
				93,
				94,
				95,
				96,
				97,
				98,
				99,
				100,
				101,
				102,
				103,
				104,
				105,
				106,
				107,
				108,
				109,
				110,
				111,
				112,
				113,
				114,
				115,
				116,
				117,
				118,
				119,
				120,
				121,
				122,
				123,
				124,
				125,
				126,
				127,
				128,
				129,
				130,
				131,
				132,
				133,
				134,
				135,
				136,
				137,
				138,
				139,
				140
			],
			"sysroot" : 
			{
				"path" : "/home/umerov/Android/Sdk/ndk/25.1.8937393/toolchains/llvm/prebuilt/linux-x86_64/sysroot"
			}
		}
	],
	"id" : "opus::@6890427a1f51a3e7e1df",
	"name" : "opus",
	"nameOnDisk" : "libopus.a",
	"paths" : 
	{
		"build" : ".",
		"source" : "."
	},
	"sourceGroups" : 
	[
		{
			"name" : "Source Files",
			"sourceIndexes" : 
			[
				0,
				1,
				2,
				3,
				4,
				5,
				6,
				7,
				8,
				9,
				10,
				11,
				12,
				13,
				14,
				15,
				16,
				17,
				18,
				19,
				20,
				21,
				22,
				23,
				24,
				25,
				26,
				27,
				28,
				29,
				30,
				31,
				32,
				33,
				34,
				35,
				36,
				37,
				38,
				39,
				40,
				41,
				42,
				43,
				44,
				45,
				46,
				47,
				48,
				49,
				50,
				51,
				52,
				53,
				54,
				55,
				56,
				57,
				58,
				59,
				60,
				61,
				62,
				63,
				64,
				65,
				66,
				67,
				68,
				69,
				70,
				71,
				72,
				73,
				74,
				75,
				76,
				77,
				78,
				79,
				80,
				81,
				82,
				83,
				84,
				85,
				86,
				87,
				88,
				89,
				90,
				91,
				92,
				93,
				94,
				95,
				96,
				97,
				98,
				99,
				100,
				101,
				102,
				103,
				104,
				105,
				106,
				107,
				108,
				109,
				110,
				111,
				112,
				113,
				114,
				115,
				116,
				117,
				118,
				119,
				120,
				121,
				122,
				123,
				124,
				125,
				126,
				127,
				128,
				129,
				130,
				131,
				132,
				133,
				134,
				135,
				136,
				137,
				138,
				139,
				140
			]
		}
	],
	"sources" : 
	[
		{
			"backtrace" : 1,
			"compileGroupIndex" : 0,
			"path" : "audio/opus/libopus/src/opus.c",
			"sourceGroupIndex" : 0
		},
		{
			"backtrace" : 1,
			"compileGroupIndex" : 0,
			"path" : "audio/opus/libopus/src/opus_decoder.c",
			"sourceGroupIndex" : 0
		},
		{
			"backtrace" : 1,
			"compileGroupIndex" : 0,
			"path" : "audio/opus/libopus/src/opus_encoder.c",
			"sourceGroupIndex" : 0
		},
		{
			"backtrace" : 1,
			"compileGroupIndex" : 0,
			"path" : "audio/opus/libopus/src/opus_multistream.c",
			"sourceGroupIndex" : 0
		},
		{
			"backtrace" : 1,
			"compileGroupIndex" : 0,
			"path" : "audio/opus/libopus/src/opus_multistream_encoder.c",
			"sourceGroupIndex" : 0
		},
		{
			"backtrace" : 1,
			"compileGroupIndex" : 0,
			"path" : "audio/opus/libopus/src/opus_multistream_decoder.c",
			"sourceGroupIndex" : 0
		},
		{
			"backtrace" : 1,
			"compileGroupIndex" : 0,
			"path" : "audio/opus/libopus/src/repacketizer.c",
			"sourceGroupIndex" : 0
		},
		{
			"backtrace" : 1,
			"compileGroupIndex" : 0,
			"path" : "audio/opus/libopus/src/analysis.c",
			"sourceGroupIndex" : 0
		},
		{
			"backtrace" : 1,
			"compileGroupIndex" : 0,
			"path" : "audio/opus/libopus/src/mlp.c",
			"sourceGroupIndex" : 0
		},
		{
			"backtrace" : 1,
			"compileGroupIndex" : 0,
			"path" : "audio/opus/libopus/src/mlp_data.c",
			"sourceGroupIndex" : 0
		},
		{
			"backtrace" : 1,
			"compileGroupIndex" : 0,
			"path" : "audio/opus/libopus/src/opus_projection_encoder.c",
			"sourceGroupIndex" : 0
		},
		{
			"backtrace" : 1,
			"compileGroupIndex" : 0,
			"path" : "audio/opus/libopus/src/opus_projection_decoder.c",
			"sourceGroupIndex" : 0
		},
		{
			"backtrace" : 1,
			"compileGroupIndex" : 0,
			"path" : "audio/opus/libopus/src/mapping_matrix.c",
			"sourceGroupIndex" : 0
		},
		{
			"backtrace" : 1,
			"compileGroupIndex" : 0,
			"path" : "audio/opus/libopus/silk/CNG.c",
			"sourceGroupIndex" : 0
		},
		{
			"backtrace" : 1,
			"compileGroupIndex" : 0,
			"path" : "audio/opus/libopus/silk/code_signs.c",
			"sourceGroupIndex" : 0
		},
		{
			"backtrace" : 1,
			"compileGroupIndex" : 0,
			"path" : "audio/opus/libopus/silk/init_decoder.c",
			"sourceGroupIndex" : 0
		},
		{
			"backtrace" : 1,
			"compileGroupIndex" : 0,
			"path" : "audio/opus/libopus/silk/decode_core.c",
			"sourceGroupIndex" : 0
		},
		{
			"backtrace" : 1,
			"compileGroupIndex" : 0,
			"path" : "audio/opus/libopus/silk/decode_frame.c",
			"sourceGroupIndex" : 0
		},
		{
			"backtrace" : 1,
			"compileGroupIndex" : 0,
			"path" : "audio/opus/libopus/silk/decode_parameters.c",
			"sourceGroupIndex" : 0
		},
		{
			"backtrace" : 1,
			"compileGroupIndex" : 0,
			"path" : "audio/opus/libopus/silk/decode_indices.c",
			"sourceGroupIndex" : 0
		},
		{
			"backtrace" : 1,
			"compileGroupIndex" : 0,
			"path" : "audio/opus/libopus/silk/decode_pulses.c",
			"sourceGroupIndex" : 0
		},
		{
			"backtrace" : 1,
			"compileGroupIndex" : 0,
			"path" : "audio/opus/libopus/silk/decoder_set_fs.c",
			"sourceGroupIndex" : 0
		},
		{
			"backtrace" : 1,
			"compileGroupIndex" : 0,
			"path" : "audio/opus/libopus/silk/dec_API.c",
			"sourceGroupIndex" : 0
		},
		{
			"backtrace" : 1,
			"compileGroupIndex" : 0,
			"path" : "audio/opus/libopus/silk/enc_API.c",
			"sourceGroupIndex" : 0
		},
		{
			"backtrace" : 1,
			"compileGroupIndex" : 0,
			"path" : "audio/opus/libopus/silk/encode_indices.c",
			"sourceGroupIndex" : 0
		},
		{
			"backtrace" : 1,
			"compileGroupIndex" : 0,
			"path" : "audio/opus/libopus/silk/encode_pulses.c",
			"sourceGroupIndex" : 0
		},
		{
			"backtrace" : 1,
			"compileGroupIndex" : 0,
			"path" : "audio/opus/libopus/silk/gain_quant.c",
			"sourceGroupIndex" : 0
		},
		{
			"backtrace" : 1,
			"compileGroupIndex" : 0,
			"path" : "audio/opus/libopus/silk/interpolate.c",
			"sourceGroupIndex" : 0
		},
		{
			"backtrace" : 1,
			"compileGroupIndex" : 0,
			"path" : "audio/opus/libopus/silk/LP_variable_cutoff.c",
			"sourceGroupIndex" : 0
		},
		{
			"backtrace" : 1,
			"compileGroupIndex" : 0,
			"path" : "audio/opus/libopus/silk/NLSF_decode.c",
			"sourceGroupIndex" : 0
		},
		{
			"backtrace" : 1,
			"compileGroupIndex" : 0,
			"path" : "audio/opus/libopus/silk/NSQ.c",
			"sourceGroupIndex" : 0
		},
		{
			"backtrace" : 1,
			"compileGroupIndex" : 0,
			"path" : "audio/opus/libopus/silk/NSQ_del_dec.c",
			"sourceGroupIndex" : 0
		},
		{
			"backtrace" : 1,
			"compileGroupIndex" : 0,
			"path" : "audio/opus/libopus/silk/PLC.c",
			"sourceGroupIndex" : 0
		},
		{
			"backtrace" : 1,
			"compileGroupIndex" : 0,
			"path" : "audio/opus/libopus/silk/shell_coder.c",
			"sourceGroupIndex" : 0
		},
		{
			"backtrace" : 1,
			"compileGroupIndex" : 0,
			"path" : "audio/opus/libopus/silk/tables_gain.c",
			"sourceGroupIndex" : 0
		},
		{
			"backtrace" : 1,
			"compileGroupIndex" : 0,
			"path" : "audio/opus/libopus/silk/tables_LTP.c",
			"sourceGroupIndex" : 0
		},
		{
			"backtrace" : 1,
			"compileGroupIndex" : 0,
			"path" : "audio/opus/libopus/silk/tables_NLSF_CB_NB_MB.c",
			"sourceGroupIndex" : 0
		},
		{
			"backtrace" : 1,
			"compileGroupIndex" : 0,
			"path" : "audio/opus/libopus/silk/tables_NLSF_CB_WB.c",
			"sourceGroupIndex" : 0
		},
		{
			"backtrace" : 1,
			"compileGroupIndex" : 0,
			"path" : "audio/opus/libopus/silk/tables_other.c",
			"sourceGroupIndex" : 0
		},
		{
			"backtrace" : 1,
			"compileGroupIndex" : 0,
			"path" : "audio/opus/libopus/silk/tables_pitch_lag.c",
			"sourceGroupIndex" : 0
		},
		{
			"backtrace" : 1,
			"compileGroupIndex" : 0,
			"path" : "audio/opus/libopus/silk/tables_pulses_per_block.c",
			"sourceGroupIndex" : 0
		},
		{
			"backtrace" : 1,
			"compileGroupIndex" : 0,
			"path" : "audio/opus/libopus/silk/VAD.c",
			"sourceGroupIndex" : 0
		},
		{
			"backtrace" : 1,
			"compileGroupIndex" : 0,
			"path" : "audio/opus/libopus/silk/control_audio_bandwidth.c",
			"sourceGroupIndex" : 0
		},
		{
			"backtrace" : 1,
			"compileGroupIndex" : 0,
			"path" : "audio/opus/libopus/silk/quant_LTP_gains.c",
			"sourceGroupIndex" : 0
		},
		{
			"backtrace" : 1,
			"compileGroupIndex" : 0,
			"path" : "audio/opus/libopus/silk/VQ_WMat_EC.c",
			"sourceGroupIndex" : 0
		},
		{
			"backtrace" : 1,
			"compileGroupIndex" : 0,
			"path" : "audio/opus/libopus/silk/HP_variable_cutoff.c",
			"sourceGroupIndex" : 0
		},
		{
			"backtrace" : 1,
			"compileGroupIndex" : 0,
			"path" : "audio/opus/libopus/silk/NLSF_encode.c",
			"sourceGroupIndex" : 0
		},
		{
			"backtrace" : 1,
			"compileGroupIndex" : 0,
			"path" : "audio/opus/libopus/silk/NLSF_VQ.c",
			"sourceGroupIndex" : 0
		},
		{
			"backtrace" : 1,
			"compileGroupIndex" : 0,
			"path" : "audio/opus/libopus/silk/NLSF_unpack.c",
			"sourceGroupIndex" : 0
		},
		{
			"backtrace" : 1,
			"compileGroupIndex" : 0,
			"path" : "audio/opus/libopus/silk/NLSF_del_dec_quant.c",
			"sourceGroupIndex" : 0
		},
		{
			"backtrace" : 1,
			"compileGroupIndex" : 0,
			"path" : "audio/opus/libopus/silk/process_NLSFs.c",
			"sourceGroupIndex" : 0
		},
		{
			"backtrace" : 1,
			"compileGroupIndex" : 0,
			"path" : "audio/opus/libopus/silk/stereo_LR_to_MS.c",
			"sourceGroupIndex" : 0
		},
		{
			"backtrace" : 1,
			"compileGroupIndex" : 0,
			"path" : "audio/opus/libopus/silk/stereo_MS_to_LR.c",
			"sourceGroupIndex" : 0
		},
		{
			"backtrace" : 1,
			"compileGroupIndex" : 0,
			"path" : "audio/opus/libopus/silk/check_control_input.c",
			"sourceGroupIndex" : 0
		},
		{
			"backtrace" : 1,
			"compileGroupIndex" : 0,
			"path" : "audio/opus/libopus/silk/control_SNR.c",
			"sourceGroupIndex" : 0
		},
		{
			"backtrace" : 1,
			"compileGroupIndex" : 0,
			"path" : "audio/opus/libopus/silk/init_encoder.c",
			"sourceGroupIndex" : 0
		},
		{
			"backtrace" : 1,
			"compileGroupIndex" : 0,
			"path" : "audio/opus/libopus/silk/control_codec.c",
			"sourceGroupIndex" : 0
		},
		{
			"backtrace" : 1,
			"compileGroupIndex" : 0,
			"path" : "audio/opus/libopus/silk/A2NLSF.c",
			"sourceGroupIndex" : 0
		},
		{
			"backtrace" : 1,
			"compileGroupIndex" : 0,
			"path" : "audio/opus/libopus/silk/ana_filt_bank_1.c",
			"sourceGroupIndex" : 0
		},
		{
			"backtrace" : 1,
			"compileGroupIndex" : 0,
			"path" : "audio/opus/libopus/silk/biquad_alt.c",
			"sourceGroupIndex" : 0
		},
		{
			"backtrace" : 1,
			"compileGroupIndex" : 0,
			"path" : "audio/opus/libopus/silk/bwexpander_32.c",
			"sourceGroupIndex" : 0
		},
		{
			"backtrace" : 1,
			"compileGroupIndex" : 0,
			"path" : "audio/opus/libopus/silk/bwexpander.c",
			"sourceGroupIndex" : 0
		},
		{
			"backtrace" : 1,
			"compileGroupIndex" : 0,
			"path" : "audio/opus/libopus/silk/debug.c",
			"sourceGroupIndex" : 0
		},
		{
			"backtrace" : 1,
			"compileGroupIndex" : 0,
			"path" : "audio/opus/libopus/silk/decode_pitch.c",
			"sourceGroupIndex" : 0
		},
		{
			"backtrace" : 1,
			"compileGroupIndex" : 0,
			"path" : "audio/opus/libopus/silk/inner_prod_aligned.c",
			"sourceGroupIndex" : 0
		},
		{
			"backtrace" : 1,
			"compileGroupIndex" : 0,
			"path" : "audio/opus/libopus/silk/lin2log.c",
			"sourceGroupIndex" : 0
		},
		{
			"backtrace" : 1,
			"compileGroupIndex" : 0,
			"path" : "audio/opus/libopus/silk/log2lin.c",
			"sourceGroupIndex" : 0
		},
		{
			"backtrace" : 1,
			"compileGroupIndex" : 0,
			"path" : "audio/opus/libopus/silk/LPC_analysis_filter.c",
			"sourceGroupIndex" : 0
		},
		{
			"backtrace" : 1,
			"compileGroupIndex" : 0,
			"path" : "audio/opus/libopus/silk/LPC_inv_pred_gain.c",
			"sourceGroupIndex" : 0
		},
		{
			"backtrace" : 1,
			"compileGroupIndex" : 0,
			"path" : "audio/opus/libopus/silk/table_LSF_cos.c",
			"sourceGroupIndex" : 0
		},
		{
			"backtrace" : 1,
			"compileGroupIndex" : 0,
			"path" : "audio/opus/libopus/silk/NLSF2A.c",
			"sourceGroupIndex" : 0
		},
		{
			"backtrace" : 1,
			"compileGroupIndex" : 0,
			"path" : "audio/opus/libopus/silk/NLSF_stabilize.c",
			"sourceGroupIndex" : 0
		},
		{
			"backtrace" : 1,
			"compileGroupIndex" : 0,
			"path" : "audio/opus/libopus/silk/NLSF_VQ_weights_laroia.c",
			"sourceGroupIndex" : 0
		},
		{
			"backtrace" : 1,
			"compileGroupIndex" : 0,
			"path" : "audio/opus/libopus/silk/pitch_est_tables.c",
			"sourceGroupIndex" : 0
		},
		{
			"backtrace" : 1,
			"compileGroupIndex" : 0,
			"path" : "audio/opus/libopus/silk/resampler.c",
			"sourceGroupIndex" : 0
		},
		{
			"backtrace" : 1,
			"compileGroupIndex" : 0,
			"path" : "audio/opus/libopus/silk/resampler_down2_3.c",
			"sourceGroupIndex" : 0
		},
		{
			"backtrace" : 1,
			"compileGroupIndex" : 0,
			"path" : "audio/opus/libopus/silk/resampler_down2.c",
			"sourceGroupIndex" : 0
		},
		{
			"backtrace" : 1,
			"compileGroupIndex" : 0,
			"path" : "audio/opus/libopus/silk/resampler_private_AR2.c",
			"sourceGroupIndex" : 0
		},
		{
			"backtrace" : 1,
			"compileGroupIndex" : 0,
			"path" : "audio/opus/libopus/silk/resampler_private_down_FIR.c",
			"sourceGroupIndex" : 0
		},
		{
			"backtrace" : 1,
			"compileGroupIndex" : 0,
			"path" : "audio/opus/libopus/silk/resampler_private_IIR_FIR.c",
			"sourceGroupIndex" : 0
		},
		{
			"backtrace" : 1,
			"compileGroupIndex" : 0,
			"path" : "audio/opus/libopus/silk/resampler_private_up2_HQ.c",
			"sourceGroupIndex" : 0
		},
		{
			"backtrace" : 1,
			"compileGroupIndex" : 0,
			"path" : "audio/opus/libopus/silk/resampler_rom.c",
			"sourceGroupIndex" : 0
		},
		{
			"backtrace" : 1,
			"compileGroupIndex" : 0,
			"path" : "audio/opus/libopus/silk/sigm_Q15.c",
			"sourceGroupIndex" : 0
		},
		{
			"backtrace" : 1,
			"compileGroupIndex" : 0,
			"path" : "audio/opus/libopus/silk/sort.c",
			"sourceGroupIndex" : 0
		},
		{
			"backtrace" : 1,
			"compileGroupIndex" : 0,
			"path" : "audio/opus/libopus/silk/sum_sqr_shift.c",
			"sourceGroupIndex" : 0
		},
		{
			"backtrace" : 1,
			"compileGroupIndex" : 0,
			"path" : "audio/opus/libopus/silk/stereo_decode_pred.c",
			"sourceGroupIndex" : 0
		},
		{
			"backtrace" : 1,
			"compileGroupIndex" : 0,
			"path" : "audio/opus/libopus/silk/stereo_encode_pred.c",
			"sourceGroupIndex" : 0
		},
		{
			"backtrace" : 1,
			"compileGroupIndex" : 0,
			"path" : "audio/opus/libopus/silk/stereo_find_predictor.c",
			"sourceGroupIndex" : 0
		},
		{
			"backtrace" : 1,
			"compileGroupIndex" : 0,
			"path" : "audio/opus/libopus/silk/stereo_quant_pred.c",
			"sourceGroupIndex" : 0
		},
		{
			"backtrace" : 1,
			"compileGroupIndex" : 0,
			"path" : "audio/opus/libopus/silk/LPC_fit.c",
			"sourceGroupIndex" : 0
		},
		{
			"backtrace" : 1,
			"compileGroupIndex" : 0,
			"path" : "audio/opus/libopus/silk/fixed/LTP_analysis_filter_FIX.c",
			"sourceGroupIndex" : 0
		},
		{
			"backtrace" : 1,
			"compileGroupIndex" : 0,
			"path" : "audio/opus/libopus/silk/fixed/LTP_scale_ctrl_FIX.c",
			"sourceGroupIndex" : 0
		},
		{
			"backtrace" : 1,
			"compileGroupIndex" : 0,
			"path" : "audio/opus/libopus/silk/fixed/corrMatrix_FIX.c",
			"sourceGroupIndex" : 0
		},
		{
			"backtrace" : 1,
			"compileGroupIndex" : 0,
			"path" : "audio/opus/libopus/silk/fixed/encode_frame_FIX.c",
			"sourceGroupIndex" : 0
		},
		{
			"backtrace" : 1,
			"compileGroupIndex" : 0,
			"path" : "audio/opus/libopus/silk/fixed/find_LPC_FIX.c",
			"sourceGroupIndex" : 0
		},
		{
			"backtrace" : 1,
			"compileGroupIndex" : 0,
			"path" : "audio/opus/libopus/silk/fixed/find_LTP_FIX.c",
			"sourceGroupIndex" : 0
		},
		{
			"backtrace" : 1,
			"compileGroupIndex" : 0,
			"path" : "audio/opus/libopus/silk/fixed/find_pitch_lags_FIX.c",
			"sourceGroupIndex" : 0
		},
		{
			"backtrace" : 1,
			"compileGroupIndex" : 0,
			"path" : "audio/opus/libopus/silk/fixed/find_pred_coefs_FIX.c",
			"sourceGroupIndex" : 0
		},
		{
			"backtrace" : 1,
			"compileGroupIndex" : 0,
			"path" : "audio/opus/libopus/silk/fixed/noise_shape_analysis_FIX.c",
			"sourceGroupIndex" : 0
		},
		{
			"backtrace" : 1,
			"compileGroupIndex" : 0,
			"path" : "audio/opus/libopus/silk/fixed/process_gains_FIX.c",
			"sourceGroupIndex" : 0
		},
		{
			"backtrace" : 1,
			"compileGroupIndex" : 0,
			"path" : "audio/opus/libopus/silk/fixed/regularize_correlations_FIX.c",
			"sourceGroupIndex" : 0
		},
		{
			"backtrace" : 1,
			"compileGroupIndex" : 0,
			"path" : "audio/opus/libopus/silk/fixed/residual_energy16_FIX.c",
			"sourceGroupIndex" : 0
		},
		{
			"backtrace" : 1,
			"compileGroupIndex" : 0,
			"path" : "audio/opus/libopus/silk/fixed/residual_energy_FIX.c",
			"sourceGroupIndex" : 0
		},
		{
			"backtrace" : 1,
			"compileGroupIndex" : 0,
			"path" : "audio/opus/libopus/silk/fixed/warped_autocorrelation_FIX.c",
			"sourceGroupIndex" : 0
		},
		{
			"backtrace" : 1,
			"compileGroupIndex" : 0,
			"path" : "audio/opus/libopus/silk/fixed/apply_sine_window_FIX.c",
			"sourceGroupIndex" : 0
		},
		{
			"backtrace" : 1,
			"compileGroupIndex" : 0,
			"path" : "audio/opus/libopus/silk/fixed/autocorr_FIX.c",
			"sourceGroupIndex" : 0
		},
		{
			"backtrace" : 1,
			"compileGroupIndex" : 0,
			"path" : "audio/opus/libopus/silk/fixed/burg_modified_FIX.c",
			"sourceGroupIndex" : 0
		},
		{
			"backtrace" : 1,
			"compileGroupIndex" : 0,
			"path" : "audio/opus/libopus/silk/fixed/k2a_FIX.c",
			"sourceGroupIndex" : 0
		},
		{
			"backtrace" : 1,
			"compileGroupIndex" : 0,
			"path" : "audio/opus/libopus/silk/fixed/k2a_Q16_FIX.c",
			"sourceGroupIndex" : 0
		},
		{
			"backtrace" : 1,
			"compileGroupIndex" : 0,
			"path" : "audio/opus/libopus/silk/fixed/pitch_analysis_core_FIX.c",
			"sourceGroupIndex" : 0
		},
		{
			"backtrace" : 1,
			"compileGroupIndex" : 0,
			"path" : "audio/opus/libopus/silk/fixed/vector_ops_FIX.c",
			"sourceGroupIndex" : 0
		},
		{
			"backtrace" : 1,
			"compileGroupIndex" : 0,
			"path" : "audio/opus/libopus/silk/fixed/schur64_FIX.c",
			"sourceGroupIndex" : 0
		},
		{
			"backtrace" : 1,
			"compileGroupIndex" : 0,
			"path" : "audio/opus/libopus/silk/fixed/schur_FIX.c",
			"sourceGroupIndex" : 0
		},
		{
			"backtrace" : 1,
			"compileGroupIndex" : 0,
			"path" : "audio/opus/libopus/celt/bands.c",
			"sourceGroupIndex" : 0
		},
		{
			"backtrace" : 1,
			"compileGroupIndex" : 0,
			"path" : "audio/opus/libopus/celt/celt.c",
			"sourceGroupIndex" : 0
		},
		{
			"backtrace" : 1,
			"compileGroupIndex" : 0,
			"path" : "audio/opus/libopus/celt/celt_encoder.c",
			"sourceGroupIndex" : 0
		},
		{
			"backtrace" : 1,
			"compileGroupIndex" : 0,
			"path" : "audio/opus/libopus/celt/celt_decoder.c",
			"sourceGroupIndex" : 0
		},
		{
			"backtrace" : 1,
			"compileGroupIndex" : 0,
			"path" : "audio/opus/libopus/celt/cwrs.c",
			"sourceGroupIndex" : 0
		},
		{
			"backtrace" : 1,
			"compileGroupIndex" : 0,
			"path" : "audio/opus/libopus/celt/entcode.c",
			"sourceGroupIndex" : 0
		},
		{
			"backtrace" : 1,
			"compileGroupIndex" : 0,
			"path" : "audio/opus/libopus/celt/entdec.c",
			"sourceGroupIndex" : 0
		},
		{
			"backtrace" : 1,
			"compileGroupIndex" : 0,
			"path" : "audio/opus/libopus/celt/entenc.c",
			"sourceGroupIndex" : 0
		},
		{
			"backtrace" : 1,
			"compileGroupIndex" : 0,
			"path" : "audio/opus/libopus/celt/kiss_fft.c",
			"sourceGroupIndex" : 0
		},
		{
			"backtrace" : 1,
			"compileGroupIndex" : 0,
			"path" : "audio/opus/libopus/celt/laplace.c",
			"sourceGroupIndex" : 0
		},
		{
			"backtrace" : 1,
			"compileGroupIndex" : 0,
			"path" : "audio/opus/libopus/celt/mathops.c",
			"sourceGroupIndex" : 0
		},
		{
			"backtrace" : 1,
			"compileGroupIndex" : 0,
			"path" : "audio/opus/libopus/celt/mdct.c",
			"sourceGroupIndex" : 0
		},
		{
			"backtrace" : 1,
			"compileGroupIndex" : 0,
			"path" : "audio/opus/libopus/celt/modes.c",
			"sourceGroupIndex" : 0
		},
		{
			"backtrace" : 1,
			"compileGroupIndex" : 0,
			"path" : "audio/opus/libopus/celt/pitch.c",
			"sourceGroupIndex" : 0
		},
		{
			"backtrace" : 1,
			"compileGroupIndex" : 0,
			"path" : "audio/opus/libopus/celt/celt_lpc.c",
			"sourceGroupIndex" : 0
		},
		{
			"backtrace" : 1,
			"compileGroupIndex" : 0,
			"path" : "audio/opus/libopus/celt/quant_bands.c",
			"sourceGroupIndex" : 0
		},
		{
			"backtrace" : 1,
			"compileGroupIndex" : 0,
			"path" : "audio/opus/libopus/celt/rate.c",
			"sourceGroupIndex" : 0
		},
		{
			"backtrace" : 1,
			"compileGroupIndex" : 0,
			"path" : "audio/opus/libopus/celt/vq.c",
			"sourceGroupIndex" : 0
		},
		{
			"backtrace" : 1,
			"compileGroupIndex" : 0,
			"path" : "audio/opus/libopus/celt/arm/armcpu.c",
			"sourceGroupIndex" : 0
		},
		{
			"backtrace" : 1,
			"compileGroupIndex" : 0,
			"path" : "audio/opus/libopus/celt/arm/arm_celt_map.c",
			"sourceGroupIndex" : 0
		},
		{
			"backtrace" : 6,
			"compileGroupIndex" : 0,
			"path" : "audio/opus/libopus/celt/arm/celt_neon_intr.c",
			"sourceGroupIndex" : 0
		},
		{
			"backtrace" : 6,
			"compileGroupIndex" : 0,
			"path" : "audio/opus/libopus/celt/arm/pitch_neon_intr.c",
			"sourceGroupIndex" : 0
		},
		{
			"backtrace" : 6,
			"compileGroupIndex" : 0,
			"path" : "audio/opus/libopus/silk/arm/NSQ_neon.c",
			"sourceGroupIndex" : 0
		},
		{
			"backtrace" : 6,
			"compileGroupIndex" : 0,
			"path" : "audio/opus/libopus/silk/arm/arm_silk_map.c",
			"sourceGroupIndex" : 0
		},
		{
			"backtrace" : 6,
			"compileGroupIndex" : 0,
			"path" : "audio/opus/libopus/silk/arm/LPC_inv_pred_gain_neon_intr.c",
			"sourceGroupIndex" : 0
		},
		{
			"backtrace" : 6,
			"compileGroupIndex" : 0,
			"path" : "audio/opus/libopus/silk/arm/NSQ_del_dec_neon_intr.c",
			"sourceGroupIndex" : 0
		},
		{
			"backtrace" : 6,
			"compileGroupIndex" : 0,
			"path" : "audio/opus/libopus/silk/arm/biquad_alt_neon_intr.c",
			"sourceGroupIndex" : 0
		},
		{
			"backtrace" : 6,
			"compileGroupIndex" : 0,
			"path" : "audio/opus/libopus/silk/fixed/arm/warped_autocorrelation_FIX_neon_intr.c",
			"sourceGroupIndex" : 0
		}
	],
	"type" : "STATIC_LIBRARY"
}
